face_auth/__init__.py
face_auth/detector.py
face_auth-1.1.dist-info/LICENSE
face_auth-1.1.dist-info/METADATA
face_auth-1.1.dist-info/WHEEL
face_auth-1.1.dist-info/top_level.txt
face_auth-1.1.dist-info/RECORD
